commondata_countries/__init__.py
commondata_countries/__main__.py
commondata_countries/data.py
commondata_countries-2.3.0.dist-info/LICENSE
commondata_countries-2.3.0.dist-info/METADATA
commondata_countries-2.3.0.dist-info/WHEEL
commondata_countries-2.3.0.dist-info/entry_points.txt
commondata_countries-2.3.0.dist-info/RECORD
