Metadata-Version: 2.3
Name: commondata-countries
Version: 2.3.0
Summary: Work with ISO 3166-1 alpha2, alpha3 and numeric standard country data
License: GPL-3.0-only
Author: Shiv Deepak
Author-email: shivdeepak@gmail.com
Requires-Python: >=3.9
Classifier: Development Status :: 4 - Beta
Classifier: Environment :: Console
Classifier: Intended Audience :: Developers
Classifier: Intended Audience :: Science/Research
Classifier: License :: OSI Approved :: GNU General Public License v3 (GPLv3)
Classifier: Operating System :: OS Independent
Classifier: Programming Language :: Python
Classifier: Programming Language :: Python :: 3
Classifier: Programming Language :: Python :: 3 :: Only
Classifier: Programming Language :: Python :: 3.9
Classifier: Programming Language :: Python :: 3.10
Classifier: Programming Language :: Python :: 3.11
Classifier: Programming Language :: Python :: 3.12
Classifier: Programming Language :: Python :: 3.13
Classifier: Topic :: Software Development :: Libraries :: Python Modules
Classifier: Topic :: Utilities
Requires-Dist: rapidfuzz (>=3.12.1,<4.0.0)
Project-URL: Documentation, https://github.com/commondata-net/commondata-countries-python/blob/main/README.md
Project-URL: Homepage, https://commondata.net/countries/
Project-URL: Release notes, https://github.com/commondata-net/commondata-countries-python/releases
Project-URL: Source, https://github.com/commondata-net/commondata-countries-python
Project-URL: Tracker, https://github.com/commondata-net/commondata-countries-python/issues
